hotopy/__init__.py
hotopy/datasets/__init__.py
hotopy/datasets/_fetcher.py
hotopy/datasets/_holograms.py
hotopy/datasets/_phantoms.py
hotopy/datasets/registry.txt
hotopy/holo/__init__.py
hotopy/holo/_ap.py
hotopy/holo/_ctf.py
hotopy/holo/_pbi.py
hotopy/holo/_pca.py
hotopy/holo/_tieregime.py
hotopy/holo/_tikhonov.py
hotopy/holo/_util.py
hotopy/holo/constraints.py
hotopy/holo/propagation.py
hotopy/holo/regularization.py
hotopy/image/__init__.py
hotopy/image/_filter.py
hotopy/image/_generators.py
hotopy/image/_inpainting.py
hotopy/image/_registration.py
hotopy/image/_stats.py
hotopy/image/_transforms.py
hotopy/optimize.py
hotopy/tomo/__init__.py
hotopy/tomo/_alignment.py
hotopy/tomo/_astra.py
hotopy/tomo/_operators.py
hotopy/tomo/_reprojection_alignment.py
hotopy/tomo/_ringremove.py
hotopy/utils/__init__.py
hotopy/utils/_io.py
hotopy/utils/_misc.py
hotopy/utils/_padding.py
hotopy/utils/_xray.py
hotopy/utils/fourier.py
hotopy-0.24.dist-info/WHEEL
hotopy-0.24.dist-info/METADATA
hotopy-0.24.dist-info/RECORD
