Metadata-Version: 2.3
Name: hotopy
Version: 0.24
Summary: A toolbox for X-ray holo-tomography in Python
Author: Jens Lucht, Paul Meyer, Leon M. Lohse
Author-email: Jens Lucht <jens.lucht@uni-goettingen.de>, Paul Meyer <paul.meyer@uni-goettingen.de>, Leon M. Lohse <llohse@uni-goettingen.de>
License: GPL-3.0-or-later
Classifier: Development Status :: 4 - Beta
Classifier: Intended Audience :: Science/Research
Classifier: Topic :: Scientific/Engineering
Classifier: Topic :: Scientific/Engineering :: Mathematics
Classifier: Topic :: Scientific/Engineering :: Physics
Classifier: Topic :: Scientific/Engineering :: Image Processing
Classifier: Programming Language :: Python :: 3
Classifier: Programming Language :: Python :: 3.10
Classifier: Programming Language :: Python :: 3.11
Classifier: Programming Language :: Python :: 3.12
Classifier: Programming Language :: Python :: 3.13
Classifier: Programming Language :: Python :: 3.14
Classifier: License :: OSI Approved :: GNU General Public License v3 or later (GPLv3+)
Classifier: Operating System :: OS Independent
Requires-Dist: matplotlib
Requires-Dist: scipy
Requires-Dist: numpy>=2
Requires-Dist: pooch>=1.2
Requires-Dist: torch
Requires-Dist: scikit-image
Requires-Dist: tqdm
Requires-Dist: ptwt
Requires-Dist: ruff>=0.7.2 ; extra == 'dev'
Requires-Dist: pre-commit>=4.1.0 ; extra == 'dev'
Requires-Dist: sphinx ; extra == 'docs'
Requires-Dist: pydata-sphinx-theme ; extra == 'docs'
Requires-Dist: sphinxcontrib-bibtex ; extra == 'docs'
Requires-Dist: nbsphinx ; extra == 'docs'
Requires-Dist: ipykernel ; extra == 'docs'
Requires-Dist: astra-toolbox>=2.4.1 ; extra == 'tomo'
Requires-Python: >=3.10
Project-URL: documentation, https://irp.pages.gwdg.de/hotopy/
Project-URL: homepage, https://gitlab.gwdg.de/irp/hotopy
Project-URL: repository, https://gitlab.gwdg.de/irp/hotopy.git
Provides-Extra: dev
Provides-Extra: docs
Provides-Extra: tomo
